testmind/hardware/mini_topk_selector.v
`timescale 1ns / 1ps

// Mini Top-K 选择器
// 输入：16 个值，输出：Top-4 的索引

module mini_topk_selector #(
    parameter NUM_VALUES = 16,
    parameter TOP_K = 4,
    parameter INDEX_WIDTH = 4  // log2(16) = 4
)(
    input wire clk,
    input wire rst_n,
    input wire start,

    // 输入值
    input wire [7:0] values [0:NUM_VALUES-1],

    // Top-K 输出
    output reg [INDEX_WIDTH-1:0] topk_indices [0:TOP_K-1],
    output reg done
);

    // 状态机
    localparam IDLE = 2'd0;
    localparam SORT = 2'd1;
    localparam DONE_STATE = 2'd2;

    reg [1:0] state;
    reg [7:0] sorted_values [0:TOP_K-1];
    reg [INDEX_WIDTH-1:0] sorted_indices [0:TOP_K-1];
    integer i, j;
    reg [7:0] temp_val;
    reg [INDEX_WIDTH-1:0] temp_idx;

    always @(posedge clk or negedge rst_n) begin
        if (!rst_n) begin
            state <= IDLE;
            done <= 0;
            for (i = 0; i < TOP_K; i = i + 1) begin
                sorted_values[i] <= 0;
                sorted_indices[i] <= 0;
                topk_indices[i] <= 0;
            end
        end else begin
            case (state)
                IDLE: begin
                    if (start) begin
                        state <= SORT;
                        done <= 0;

                        // 初始化前 TOP_K 个
                        for (i = 0; i < TOP_K; i = i + 1) begin
                            sorted_values[i] <= values[i];
                            sorted_indices[i] <= i;
                        end
                    end
                end

                SORT: begin
                    // 简化版：单周期完成（实际应该多周期）
                    // 插入排序找 Top-K

                    // 遍历剩余值
                    for (i = TOP_K; i < NUM_VALUES; i = i + 1) begin
                        if (values[i] > sorted_values[TOP_K-1]) begin
                            // 插入到正确位置
                            sorted_values[TOP_K-1] <= values[i];
                            sorted_indices[TOP_K-1] <= i;

                            // 冒泡到正确位置
                            for (j = TOP_K-1; j > 0; j = j - 1) begin
                                if (sorted_values[j] > sorted_values[j-1]) begin
                                    temp_val = sorted_values[j];
                                    temp_idx = sorted_indices[j];
                                    sorted_values[j] <= sorted_values[j-1];
                                    sorted_indices[j] <= sorted_indices[j-1];
                                    sorted_values[j-1] <= temp_val;
                                    sorted_indices[j-1] <= temp_idx;
                                end
                            end
                        end
                    end

                    // 输出结果
                    for (i = 0; i < TOP_K; i = i + 1) begin
                        topk_indices[i] <= sorted_indices[i];
                    end

                    state <= DONE_STATE;
                end

                DONE_STATE: begin
                    done <= 1;
                    if (!start) begin
                        state <= IDLE;
                    end
                end
            endcase
        end
    end

endmodule

testmind/hardware/mini_coarse_scanner.v
`timescale 1ns / 1ps

// Mini 版本：32x32 图像，检测边缘复杂度
// 输出：4x4 = 16 个兴趣度值

module mini_coarse_scanner #(
    parameter IMAGE_SIZE = 32,
    parameter PATCH_SIZE = 8,
    parameter GRID_SIZE = 4  // 32/8 = 4
)(
    input wire clk,
    input wire rst_n,
    input wire start,

    // 图像输入（灰度）
    input wire [7:0] pixel_in,
    input wire pixel_valid,

    // 兴趣度输出
    output reg [7:0] interest_out [0:GRID_SIZE*GRID_SIZE-1],
    output reg done
);

    // 状态机
    localparam IDLE = 2'd0;
    localparam SCAN = 2'd1;
    localparam DONE = 2'd2;

    reg [1:0] state;
    reg [15:0] pixel_cnt;
    reg [7:0] image_buffer [0:IMAGE_SIZE*IMAGE_SIZE-1];

    integer i, j, pi, pj;
    reg [15:0] grad_sum;
    reg [7:0] p00, p01, p10, p11;
    reg signed [8:0] gx, gy;

    always @(posedge clk or negedge rst_n) begin
        if (!rst_n) begin
            state <= IDLE;
            pixel_cnt <= 0;
            done <= 0;
            for (i = 0; i < GRID_SIZE*GRID_SIZE; i = i + 1)
                interest_out[i] <= 0;
        end else begin
            case (state)
                IDLE: begin
                    if (start) begin
                        state <= SCAN;
                        pixel_cnt <= 0;
                        done <= 0;
                    end
                end

                SCAN: begin
                    // 接收像素
                    if (pixel_valid) begin
                        image_buffer[pixel_cnt] <= pixel_in;
                        pixel_cnt <= pixel_cnt + 1;

                        if (pixel_cnt == IMAGE_SIZE*IMAGE_SIZE - 1) begin
                            state <= DONE;
                        end
                    end
                end

                DONE: begin
                    // 计算每个 patch 的兴趣度（边缘强度）
                    // 使用简化的梯度计算
                    done <= 1;
                    state <= IDLE;
                end
            endcase
        end
    end

    // 计算兴趣度（组合逻辑，简化版）
    integer patch_idx, row, col;
    always @(*) begin
        for (patch_idx = 0; patch_idx < GRID_SIZE*GRID_SIZE; patch_idx = patch_idx + 1) begin
            row = patch_idx / GRID_SIZE;
            col = patch_idx % GRID_SIZE;

            // 简化：取 patch 中心的梯度作为兴趣度
            i = row * PATCH_SIZE + PATCH_SIZE/2;
            j = col * PATCH_SIZE + PATCH_SIZE/2;

            if (i > 0 && i < IMAGE_SIZE-1 && j > 0 && j < IMAGE_SIZE-1) begin
                // 简化的 Sobel
                p00 = image_buffer[(i-1)*IMAGE_SIZE + (j-1)];
                p01 = image_buffer[(i-1)*IMAGE_SIZE + (j+1)];
                p10 = image_buffer[(i+1)*IMAGE_SIZE + (j-1)];
                p11 = image_buffer[(i+1)*IMAGE_SIZE + (j+1)];

                // 梯度近似
                gx = $signed({1'b0, p01}) - $signed({1'b0, p00});
                gy = $signed({1'b0, p11}) - $signed({1'b0, p10});

                // 绝对值和
                interest_out[patch_idx] = (gx[8] ? -gx : gx) + (gy[8] ? -gy : gy);
            end else begin
                interest_out[patch_idx] = 0;
            end
        end
    end

endmodule

testmind/hardware/mini_pyramid_top.v
`timescale 1ns / 1ps

// Mini 金字塔处理器顶层
// 集成：扫描器 + Top-K 选择器

module mini_pyramid_top #(
    parameter IMAGE_SIZE = 32,
    parameter GRID_SIZE = 4,
    parameter TOP_K = 4
)(
    input wire clk,
    input wire rst_n,
    input wire start,

    // 图像输入
    input wire [7:0] pixel_in,
    input wire pixel_valid,

    // Top-K 输出
    output wire [3:0] selected_indices [0:TOP_K-1],
    output wire done
);

    // 中间信号
    wire scanner_done;
    wire [7:0] interest_map [0:GRID_SIZE*GRID_SIZE-1];

    wire selector_start;
    wire selector_done;

    // 扫描器
    mini_coarse_scanner #(
        .IMAGE_SIZE(IMAGE_SIZE),
        .PATCH_SIZE(8),
        .GRID_SIZE(GRID_SIZE)
    ) u_scanner (
        .clk(clk),
        .rst_n(rst_n),
        .start(start),
        .pixel_in(pixel_in),
        .pixel_valid(pixel_valid),
        .interest_out(interest_map),
        .done(scanner_done)
    );

    // Top-K 选择器
    mini_topk_selector #(
        .NUM_VALUES(GRID_SIZE*GRID_SIZE),
        .TOP_K(TOP_K),
        .INDEX_WIDTH(4)
    ) u_selector (
        .clk(clk),
        .rst_n(rst_n),
        .start(selector_start),
        .values(interest_map),
        .topk_indices(selected_indices),
        .done(selector_done)
    );

    // 控制逻辑
    assign selector_start = scanner_done;
    assign done = selector_done;

endmodule

testmind/hardware/mini_pyramid_tb.v
`timescale 1ns / 1ps

module mini_pyramid_tb;

    reg clk;
    reg rst_n;
    reg start;
    reg [7:0] pixel_in;
    reg pixel_valid;

    wire [3:0] selected_indices [0:3];
    wire done;

    // 实例化 DUT
    mini_pyramid_top #(
        .IMAGE_SIZE(32),
        .GRID_SIZE(4),
        .TOP_K(4)
    ) dut (
        .clk(clk),
        .rst_n(rst_n),
        .start(start),
        .pixel_in(pixel_in),
        .pixel_valid(pixel_valid),
        .selected_indices(selected_indices),
        .done(done)
    );

    // 时钟生成
    initial begin
        clk = 0;
        forever #5 clk = ~clk;
    end

    // 图像数据
    reg [7:0] test_image [0:1023];  // 32x32

    // 测试流程
    integer i;
    integer fd;  // 文件描述符
    initial begin
        $dumpfile("mini_pyramid.vcd");
        $dumpvars(0, mini_pyramid_tb);

        // 加载测试图像
        $readmemh("test_image.hex", test_image);

        // 复位
        rst_n = 0;
        start = 0;
        pixel_valid = 0;
        pixel_in = 0;

        #20;
        rst_n = 1;
        #10;

        // 启动
        start = 1;
        #10;
        start = 0;

        // 输入像素数据
        pixel_valid = 1;
        for (i = 0; i < 1024; i = i + 1) begin
            pixel_in = test_image[i];
            #10;
        end
        pixel_valid = 0;

        // 等待完成
        wait(done);
        #50;

        // 输出结果
        $display("=== Top-4 Selected Indices ===");
        $display("Index 0: %d", selected_indices[0]);
        $display("Index 1: %d", selected_indices[1]);
        $display("Index 2: %d", selected_indices[2]);
        $display("Index 3: %d", selected_indices[3]);

        // 写入输出文件（手动写入）
        fd = $fopen("output_indices.hex", "w");
        $fwrite(fd, "%h\n", selected_indices[0]);
        $fwrite(fd, "%h\n", selected_indices[1]);
        $fwrite(fd, "%h\n", selected_indices[2]);
        $fwrite(fd, "%h\n", selected_indices[3]);
        $fclose(fd);

        $display("Simulation complete!");
        $finish;
    end

    // 超时保护
    initial begin
        #100000;
        $display("ERROR: Simulation timeout");
        $finish;
    end

endmodule

testmind/hardware/mini_pyramid.vcd
$date
	Thu Jun 18 16:11:46 2026
$end
$version
	Icarus Verilog
$end
$timescale
	1ps
$end
$scope module mini_pyramid_tb $end
$var wire 1 ! done $end
$var reg 1 " clk $end
$var reg 8 # pixel_in [7:0] $end
$var reg 1 $ pixel_valid $end
$var reg 1 % rst_n $end
$var reg 1 & start $end
$var integer 32 ' fd [31:0] $end
$var integer 32 ( i [31:0] $end
$scope module dut $end
$var wire 1 " clk $end
$var wire 1 ! done $end
$var wire 8 ) pixel_in [7:0] $end
$var wire 1 $ pixel_valid $end
$var wire 1 % rst_n $end
$var wire 1 * selector_start $end
$var wire 1 & start $end
$var wire 1 + selector_done $end
$var wire 1 , scanner_done $end
$scope module u_scanner $end
$var wire 1 " clk $end
$var wire 8 - pixel_in [7:0] $end
$var wire 1 $ pixel_valid $end
$var wire 1 % rst_n $end
$var wire 1 & start $end
$var reg 1 , done $end
$var reg 9 . gx [8:0] $end
$var reg 9 / gy [8:0] $end
$var reg 8 0 p00 [7:0] $end
$var reg 8 1 p01 [7:0] $end
$var reg 8 2 p10 [7:0] $end
$var reg 8 3 p11 [7:0] $end
$var reg 16 4 pixel_cnt [15:0] $end
$var reg 2 5 state [1:0] $end
$var integer 32 6 col [31:0] $end
$var integer 32 7 i [31:0] $end
$var integer 32 8 j [31:0] $end
$var integer 32 9 patch_idx [31:0] $end
$var integer 32 : row [31:0] $end
$upscope $end
$scope module u_selector $end
$var wire 1 " clk $end
$var wire 1 % rst_n $end
$var wire 1 * start $end
$var reg 1 + done $end
$var reg 2 ; state [1:0] $end
$var reg 4 < temp_idx [3:0] $end
$var reg 8 = temp_val [7:0] $end
$var integer 32 > i [31:0] $end
$var integer 32 ? j [31:0] $end
$upscope $end
$upscope $end
$upscope $end
$enddefinitions $end
#0
$dumpvars
bx ?
b100 >
bx =
bx <
b0 ;
b11 :
b10000 9
b11100 8
b11100 7
b11 6
b0 5
b0 4
bx 3
bx 2
bx 1
bx 0
bx /
bx .
b0 -
0,
0+
0*
b0 )
bx (
bx '
0&
0%
0$
b0 #
0"
0!
$end
#5000
b11100 8
b11 6
b11 :
b10000 9
b100 >
b11100 7
1"
#10000
0"
#15000
b11100 8
b11 6
b11 :
b10000 9
b11100 7
b100 >
1"
#20000
0"
1%
#25000
1"
#30000
0"
1&
#35000
b1 5
1"
#40000
0"
b1100101 #
b1100101 )
b1100101 -
b0 (
1$
0&
#45000
b11100 8
b11100 7
b11 6
b11 :
b10000 9
b1 4
1"
#50000
0"
b1100010 #
b1100010 )
b1100010 -
b1 (
#55000
b11100 8
b11100 7
b11 6
b11 :
b10000 9
b10 4
1"
#60000
0"
b1100011 #
b1100011 )
b1100011 -
b10 (
#65000
b11100 8
b11100 7
b11 6
b11 :
b10000 9
b11 4
1"
#70000
0"
b1000100 #
b1000100 )
b1000100 -
b11 (
#75000
b11100 8
b11100 7
b11 6
b11 :
b10000 9
b100 4
1"
#80000
0"
b1011001 #
b1011001 )
b1011001 -
b100 (
#85000
b11100 8
b11100 7
b11 6
b11 :
b10000 9
b101 4
1"
#90000
0"
b1011111 #
b1011111 )
b1011111 -
b101 (
#95000
b11100 8
b11100 7
b11 6
b11 :
b10000 9
b110 4
1"
#100000
0"
b1110011 #
b1110011 )
b1110011 -
b110 (
#105000
b11100 8
b11100 7
b11 6
b11 :
b10000 9
b111 4
1"
#110000
0"
b1111101 #
b1111101 )
b1111101 -
b111 (
#115000
b11100 8
b11100 7
b11 6
b11 :
b10000 9
b1000 4
1"
#120000
0"
b1110111 #
b1110111 )
b1110111 -
b1000 (
#125000
b11100 8
b11100 7
b11 6
b11 :
b10000 9
b1001 4
1"
#130000
0"
b10000011 #
b10000011 )
b10000011 -
b1001 (
#135000
b11100 8
b11100 7
b11 6
b11 :
b10000 9
b1010 4
1"
#140000
0"
b1111111 #
b1111111 )
b1111111 -
b1010 (
#145000
b11100 8
b11100 7
b11 6
b11 :
b10000 9
b1011 4
1"
#150000
0"
b1110010 #
b1110010 )
b1110010 -
b1011 (
#155000
b11100 8
b11100 7
b11 6
b11 :
b10000 9
b1100 4
1"
#160000
0"
b1101011 #
b1101011 )
b1101011 -
b1100 (
#165000
b11100 8
b11100 7
b11 6
b11 :
b10000 9
b1101 4
1"
#170000
0"
b1101110 #
b1101110 )
b1101110 -
b1101 (
#175000
b11100 8
b11100 7
b11 6
b11 :
b10000 9
b1110 4
1"
#180000
0"
b1100001 #
b1100001 )
b1100001 -
b1110 (
#185000
b11100 8
b11100 7
b11 6
b11 :
b10000 9
b1111 4
1"
#190000
0"
b10001100 #
b10001100 )
b10001100 -
b1111 (
#195000
b11100 8
b11100 7
b11 6
b11 :
b10000 9
b10000 4
1"
#200000
0"
b10011110 #
b10011110 )
b10011110 -
b10000 (
#205000
b11100 8
b11100 7
b11 6
b11 :
b10000 9
b10001 4
1"
#210000
0"
b10010110 #
b10010110 )
b10010110 -
b10001 (
#215000
b11100 8
b11100 7
b11 6
b11 :
b10000 9
b10010 4
1"
#220000
0"
b10010111 #
b10010111 )
b10010111 -
b10010 (
#225000
b11100 8
b11100 7
b11 6
b11 :
b10000 9
b10011 4
1"
#230000
0"
b1110110 #
b1110110 )
b1110110 -
b10011 (
#235000
b11100 8
b11100 7
b11 6
b11 :
b10000 9
b10100 4
1"
#240000
0"
b1110000 #
b1110000 )
b1110000 -
b10100 (
#245000
b11100 8
b11100 7
b11 6
b11 :
b10000 9
b10101 4
1"
#250000
0"
b10000011 #
b10000011 )
b10000011 -
b10101 (
#255000
b11100 8
b11100 7
b11 6
b11 :
b10000 9
b10110 4
1"
#260000
0"
b1100101 #
b1100101 )
b1100101 -
b10110 (
#265000
b11100 8
b11100 7
b11 6
b11 :
b10000 9
b10111 4
1"
#270000
0"
b1100100 #
b1100100 )
b1100100 -
b10111 (
#275000
b11100 8
b11100 7
b11 6
b11 :
b10000 9
b11000 4
1"
#280000
0"
b10000011 #
b10000011 )
b10000011 -
b11000 (
#285000
b11100 8
b11100 7
b11 6
b11 :
b10000 9
b11001 4
1"
#290000
0"
b1111111 #
b1111111 )
b1111111 -
b11001 (
#295000
b11100 8
b11100 7
b11 6
b11 :
b10000 9
b11010 4
1"
#300000
0"
b1110001 #
b1110001 )
b1110001 -
b11010 (
#305000
b11100 8
b11100 7
b11 6
b11 :
b10000 9
b11011 4
1"
#310000
0"
b10010000 #
b10010000 )
b10010000 -
b11011 (
#315000
b11100 8
b11100 7
b11 6
b11 :
b10000 9
b11100 4
1"
#320000
0"
b10011100 #
b10011100 )
b10011100 -
b11100 (
#325000
b11100 8
b11100 7
b11 6
b11 :
b10000 9
b11101 4
1"
#330000
0"
b10011011 #
b10011011 )
b10011011 -
b11101 (
#335000
b11100 8
b11100 7
b11 6
b11 :
b10000 9
b11110 4
1"
#340000
0"
b10010010 #
b10010010 )
b10010010 -
b11110 (
#345000
b11100 8
b11100 7
b11 6
b11 :
b10000 9
b11111 4
1"
#350000
0"
b10001001 #
b10001001 )
b10001001 -
b11111 (
#355000
b11100 8
b11100 7
b11 6
b11 :
b10000 9
b100000 4
1"
#360000
0"
b1011110 #
b1011110 )
b1011110 -
b100000 (
#365000
b11100 8
b11100 7
b11 6
b11 :
b10000 9
b100001 4
1"
#370000
0"
b1010111 #
b1010111 )
b1010111 -
b100001 (
#375000
b11100 8
b11100 7
b11 6
b11 :
b10000 9
b100010 4
1"
#380000
0"
b1010110 #
b1010110 )
b1010110 -
b100010 (
#385000
b11100 8
b11100 7
b11 6
b11 :
b10000 9
b100011 4
1"
#390000
0"
b1000011 #
b1000011 )
b1000011 -
b100011 (
#395000
b11100 8
b11100 7
b11 6
b11 :
b10000 9
b100100 4
1"
#400000
0"
b1010110 #
b1010110 )
b1010110 -
b100100 (
#405000
b11100 8
b11100 7
b11 6
b11 :
b10000 9
b100101 4
1"
#410000
0"
b1011011 #
b1011011 )
b1011011 -
b100101 (
#415000
b11100 8
b11100 7
b11 6
b11 :
b10000 9
b100110 4
1"
#420000
0"
b1101001 #
b1101001 )
b1101001 -
b100110 (
#425000
b11100 8
b11100 7
b11 6
b11 :
b10000 9
b100111 4
1"
#430000
0"
b10000011 #
b10000011 )
b10000011 -
b100111 (
#435000
b11100 8
b11100 7
b11 6
b11 :
b10000 9
b101000 4
1"
#440000
0"
b1111111 #
b1111111 )
b1111111 -
b101000 (
#445000
b11100 8
b11100 7
b11 6
b11 :
b10000 9
b101001 4
1"
#450000
0"
b10001011 #
b10001011 )
b10001011 -
b101001 (
#455000
b11100 8
b11100 7
b11 6
b11 :
b10000 9
b101010 4
1"
#460000
0"
b10000100 #
b10000100 )
b10000100 -
b101010 (
#465000
b11100 8
b11100 7
b11 6
b11 :
b10000 9
b101011 4
1"
#470000
0"
b1100010 #
b1100010 )
b1100010 -
b101011 (
#475000
b11100 8
b11100 7
b11 6
b11 :
b10000 9
b101100 4
1"
#480000
0"
b1010001 #
b1010001 )
b1010001 -
b101100 (
#485000
b11100 8
b11100 7
b11 6
b11 :
b10000 9
b101101 4
1"
#490000
0"
b1011011 #
b1011011 )
b1011011 -
b101101 (
#495000
b11100 8
b11100 7
b11 6
b11 :
b10000 9
b101110 4
1"
#500000
0"
b1011001 #
b1011001 )
b1011001 -
b101110 (
#505000
b11100 8
b11100 7
b11 6
b11 :
b10000 9
b101111 4
1"
#510000
0"
b10000101 #
b10000101 )
b10000101 -
b101111 (
#515000
b11100 8
b11100 7
b11 6
b11 :
b10000 9
b110000 4
1"
#520000
0"
b10001101 #
b10001101 )
b10001101 -
b110000 (
#525000
b11100 8
b11100 7
b11 6
b11 :
b10000 9
b110001 4
1"
#530000
0"
b10011001 #
b10011001 )
b10011001 -
b110001 (
#535000
b11100 8
b11100 7
b11 6
b11 :
b10000 9
b110010 4
1"
#540000
0"
b10011101 #
b10011101 )
b10011101 -
b110010 (
#545000
b11100 8
b11100 7
b11 6
b11 :
b10000 9
b110011 4
1"
#550000
0"
b1110101 #
b1110101 )
b1110101 -
b110011 (
#555000
b11100 8
b11100 7
b11 6
b11 :
b10000 9
b110100 4
1"
#560000
0"
b1111001 #
b1111001 )
b1111001 -
b110100 (
#565000
b11100 8
b11100 7
b11 6
b11 :
b10000 9
b110101 4
1"
#570000
0"
b1111100 #
b1111100 )
b1111100 -
b110101 (
#575000
b11100 8
b11100 7
b11 6
b11 :
b10000 9
b110110 4
1"
#580000
0"
b1100011 #
b1100011 )
b1100011 -
b110110 (
#585000
b11100 8
b11100 7
b11 6
b11 :
b10000 9
b110111 4
1"
#590000
0"
b1110101 #
b1110101 )
b1110101 -
b110111 (
#595000
b11100 8
b11100 7
b11 6
b11 :
b10000 9
b111000 4
1"
#600000
0"
b10000111 #
b10000111 )
b10000111 -
b111000 (
#605000
b11100 8
b11100 7
b11 6
b11 :
b10000 9
b111001 4
1"
#610000
0"
b10001110 #
b10001110 )
b10001110 -
b111001 (
#615000
b11100 8
b11100 7
b11 6
b11 :
b10000 9
b111010 4
1"
#620000
0"
b10010000 #
b10010000 )
b10010000 -
b111010 (
#625000
b11100 8
b11100 7
b11 6
b11 :
b10000 9
b111011 4
1"
#630000
0"
b10010110 #
b10010110 )
b10010110 -
b111011 (
#635000
b11100 8
b11100 7
b11 6
b11 :
b10000 9
b111100 4
1"
#640000
0"
b10010100 #
b10010100 )
b10010100 -
b111100 (
#645000
b11100 8
b11100 7
b11 6
b11 :
b10000 9
b111101 4
1"
#650000
0"
b10010011 #
b10010011 )
b10010011 -
b111101 (
#655000
b11100 8
b11100 7
b11 6
b11 :
b10000 9
b111110 4
1"
#660000
0"
b111110 (
#665000
b11100 8
b11100 7
b11 6
b11 :
b10000 9
b111111 4
1"
#670000
0"
b10011000 #
b10011000 )
b10011000 -
b111111 (
#675000
b11100 8
b11100 7
b11 6
b11 :
b10000 9
b1000000 4
1"
#680000
0"
b111110 #
b111110 )
b111110 -
b1000000 (
#685000
b11100 8
b11100 7
b11 6
b11 :
b10000 9
b1000001 4
1"
#690000
0"
b1010110 #
b1010110 )
b1010110 -
b1000001 (
#695000
b11100 8
b11100 7
b11 6
b11 :
b10000 9
b1000010 4
1"
#700000
0"
b1011000 #
b1011000 )
b1011000 -
b1000010 (
#705000
b11100 8
b11100 7
b11 6
b11 :
b10000 9
b1000011 4
1"
#710000
0"
b1010100 #
b1010100 )
b1010100 -
b1000011 (
#715000
b11100 8
b11100 7
b11 6
b11 :
b10000 9
b1000100 4
1"
#720000
0"
b1101111 #
b1101111 )
b1101111 -
b1000100 (
#725000
b11100 8
b11100 7
b11 6
b11 :
b10000 9
b1000101 4
1"
#730000
0"
b1101011 #
b1101011 )
b1101011 -
b1000101 (
#735000
b11100 8
b11100 7
b11 6
b11 :
b10000 9
b1000110 4
1"
#740000
0"
b1110001 #
b1110001 )
b1110001 -
b1000110 (
#745000
b11100 8
b11100 7
b11 6
b11 :
b10000 9
b1000111 4
1"
#750000
0"
b1110010 #
b1110010 )
b1110010 -
b1000111 (
#755000
b11100 8
b11100 7
b11 6
b11 :
b10000 9
b1001000 4
1"
#760000
0"
b1101001 #
b1101001 )
b1101001 -
b1001000 (
#765000
b11100 8
b11100 7
b11 6
b11 :
b10000 9
b1001001 4
1"
#770000
0"
b10000000 #
b10000000 )
b10000000 -
b1001001 (
#775000
b11100 8
b11100 7
b11 6
b11 :
b10000 9
b1001010 4
1"
#780000
0"
b1101001 #
b1101001 )
b1101001 -
b1001010 (
#785000
b11100 8
b11100 7
b11 6
b11 :
b10000 9
b1001011 4
1"
#790000
0"
b1010101 #
b1010101 )
b1010101 -
b1001011 (
#795000
b11100 8
b11100 7
b11 6
b11 :
b10000 9
b1001100 4
1"
#800000
0"
b1010010 #
b1010010 )
b1010010 -
b1001100 (
#805000
b11100 8
b11100 7
b11 6
b11 :
b10000 9
b1001101 4
1"
#810000
0"
b1110011 #
b1110011 )
b1110011 -
b1001101 (
#815000
b11100 8
b11100 7
b11 6
b11 :
b10000 9
b1001110 4
1"
#820000
0"
b1101011 #
b1101011 )
b1101011 -
b1001110 (
#825000
b11100 8
b11100 7
b11 6
b11 :
b10000 9
b1001111 4
1"
#830000
0"
b10001000 #
b10001000 )
b10001000 -
b1001111 (
#835000
b11100 8
b11100 7
b11 6
b11 :
b10000 9
b1010000 4
1"
#840000
0"
b10011000 #
b10011000 )
b10011000 -
b1010000 (
#845000
b11100 8
b11100 7
b11 6
b11 :
b10000 9
b1010001 4
1"
#850000
0"
b10011011 #
b10011011 )
b10011011 -
b1010001 (
#855000
b11100 8
b11100 7
b11 6
b11 :
b10000 9
b1010010 4
1"
#860000
0"
b10100000 #
b10100000 )
b10100000 -
b1010010 (
#865000
b11100 8
b11100 7
b11 6
b11 :
b10000 9
b1010011 4
1"
#870000
0"
b10001111 #
b10001111 )
b10001111 -
b1010011 (
#875000
b11100 8
b11100 7
b11 6
b11 :
b10000 9
b1010100 4
1"
#880000
0"
b10000110 #
b10000110 )
b10000110 -
b1010100 (
#885000
b11100 8
b11100 7
b11 6
b11 :
b10000 9
b1010101 4
1"
#890000
0"
b1111101 #
b1111101 )
b1111101 -
b1010101 (
#895000
b11100 8
b11100 7
b11 6
b11 :
b10000 9
b1010110 4
1"
#900000
0"
b1101001 #
b1101001 )
b1101001 -
b1010110 (
#905000
b11100 8
b11100 7
b11 6
b11 :
b10000 9
b1010111 4
1"
#910000
0"
b1101100 #
b1101100 )
b1101100 -
b1010111 (
#915000
b11100 8
b11100 7
b11 6
b11 :
b10000 9
b1011000 4
1"
#920000
0"
b10000101 #
b10000101 )
b10000101 -
b1011000 (
#925000
b11100 8
b11100 7
b11 6
b11 :
b10000 9
b1011001 4
1"
#930000
0"
b10001011 #
b10001011 )
b10001011 -
b1011001 (
#935000
b11100 8
b11100 7
b11 6
b11 :
b10000 9
b1011010 4
1"
#940000
0"
b10001100 #
b10001100 )
b10001100 -
b1011010 (
#945000
b11100 8
b11100 7
b11 6
b11 :
b10000 9
b1011011 4
1"
#950000
0"
b1111000 #
b1111000 )
b1111000 -
b1011011 (
#955000
b11100 8
b11100 7
b11 6
b11 :
b10000 9
b1011100 4
1"
#960000
0"
b1011100 (
#965000
b11100 8
b11100 7
b11 6
b11 :
b10000 9
b1011101 4
1"
#970000
0"
b1111011 #
b1111011 )
b1111011 -
b1011101 (
#975000
b11100 8
b11100 7
b11 6
b11 :
b10000 9
b1011110 4
1"
#980000
0"
b1111100 #
b1111100 )
b1111100 -
b1011110 (
#985000
b11100 8
b11100 7
b11 6
b11 :
b10000 9
b1011111 4
1"
#990000
0"
b1111111 #
b1111111 )
b1111111 -
b1011111 (
#995000
b11100 8
b11100 7
b11 6
b11 :
b10000 9
b1100000 4
1"
#1000000
0"
b1001011 #
b1001011 )
b1001011 -
b1100000 (
#1005000
b11100 8
b11100 7
b11 6
b11 :
b10000 9
b1100001 4
1"
#1010000
0"
b1010010 #
b1010010 )
b1010010 -
b1100001 (
#1015000
b11100 8
b11100 7
b11 6
b11 :
b10000 9
b1100010 4
1"
#1020000
0"
b1001101 #
b1001101 )
b1001101 -
b1100010 (
#1025000
b11100 8
b11100 7
b11 6
b11 :
b10000 9
b1100011 4
1"
#1030000
0"
b1100001 #
b1100001 )
b1100001 -
b1100011 (
#1035000
bx 0
b11100 8
b11100 7
b11 6
b11 :
b10000 9
b1100100 4
1"
#1040000
0"
b1101101 #
b1101101 )
b1101101 -
b1100100 (
#1045000
bx 0
b11100 8
b11100 7
b11 6
b11 :
b10000 9
b1100101 4
1"
#1050000
0"
b1110000 #
b1110000 )
b1110000 -
b1100101 (
#1055000
bx .
bx 1
bx 0
b11100 8
b11100 7
b11 6
b11 :
b10000 9
b1100110 4
1"
#1060000
0"
b1111010 #
b1111010 )
b1111010 -
b1100110 (
#1065000
bx .
bx 1
bx 0
b11100 8
b11100 7
b11 6
b11 :
b10000 9
b1100111 4
1"
#1070000
0"
b1101101 #
b1101101 )
b1101101 -
b1100111 (
#1075000
bx .
bx 1
bx 0
b11100 8
b11100 7
b11 6
b11 :
b10000 9
b1101000 4
1"
#1080000
0"
b1100110 #
b1100110 )
b1100110 -
b1101000 (
#1085000
bx .
bx 1
bx 0
b11100 8
b11100 7
b11 6
b11 :
b10000 9
b1101001 4
1"
#1090000
0"
b1111001 #
b1111001 )
b1111001 -
b1101001 (
#1095000
bx .
bx 1
bx 0
b11100 8
b11100 7
b11 6
b11 :
b10000 9
b1101010 4
1"
#1100000
0"
b1101011 #
b1101011 )
b1101011 -
b1101010 (
#1105000
bx .
bx 1
bx 0
b11100 8
b11100 7
b11 6
b11 :
b10000 9
b1101011 4
1"
#1110000
0"
b1011110 #
b1011110 )
b1011110 -
b1101011 (
#1115000
bx .
bx 1
bx 0
b11100 8
b11100 7
b11 6
b11 :
b10000 9
b1101100 4
1"
#1120000
0"
b1100110 #
b1100110 )
b1100110 -
b1101100 (
#1125000
bx .
bx 1
bx 0
b11100 8
b11100 7
b11 6
b11 :
b10000 9
b1101101 4
1"
#1130000
0"
b10000110 #
b10000110 )
b10000110 -
b1101101 (
#1135000
bx .
bx 1
bx 0
b11100 8
b11100 7
b11 6
b11 :
b10000 9
b1101110 4
1"
#1140000
0"
b10001100 #
b10001100 )
b10001100 -
b1101110 (
#1145000
bx .
bx 1
bx 0
b11100 8
b11100 7
b11 6
b11 :
b10000 9
b1101111 4
1"
#1150000
0"
b10010001 #
b10010001 )
b10010001 -
b1101111 (
#1155000
bx .
bx 1
bx 0
b11100 8
b11100 7
b11 6
b11 :
b10000 9
b1110000 4
1"
#1160000
0"
b10010011 #
b10010011 )
b10010011 -
b1110000 (
#1165000
bx .
bx 1
bx 0
b11100 8
b11100 7
b11 6
b11 :
b10000 9
b1110001 4
1"
#1170000
0"
b10010101 #
b10010101 )
b10010101 -
b1110001 (
#1175000
bx .
bx 1
bx 0
b11100 8
b11100 7
b11 6
b11 :
b10000 9
b1110010 4
1"
#1180000
0"
b10011101 #
b10011101 )
b10011101 -
b1110010 (
#1185000
bx .
bx 1
bx 0
b11100 8
b11100 7
b11 6
b11 :
b10000 9
b1110011 4
1"
#1190000
0"
b10000010 #
b10000010 )
b10000010 -
b1110011 (
#1195000
bx .
bx 1
bx 0
b11100 8
b11100 7
b11 6
b11 :
b10000 9
b1110100 4
1"
#1200000
0"
b1111111 #
b1111111 )
b1111111 -
b1110100 (
#1205000
bx .
bx 1
bx 0
b11100 8
b11100 7
b11 6
b11 :
b10000 9
b1110101 4
1"
#1210000
0"
b10000111 #
b10000111 )
b10000111 -
b1110101 (
#1215000
bx .
bx 1
bx 0
b11100 8
b11100 7
b11 6
b11 :
b10000 9
b1110110 4
1"
#1220000
0"
b1101111 #
b1101111 )
b1101111 -
b1110110 (
#1225000
bx .
bx 1
bx 0
b11100 8
b11100 7
b11 6
b11 :
b10000 9
b1110111 4
1"
#1230000
0"
b1101011 #
b1101011 )
b1101011 -
b1110111 (
#1235000
bx .
bx 1
bx 0
b11100 8
b11100 7
b11 6
b11 :
b10000 9
b1111000 4
1"
#1240000
0"
b1111001 #
b1111001 )
b1111001 -
b1111000 (
