rtl/periph/vlm/vlm_topk_selector.v
`timescale 1ns / 1ps

// 超简化 Top-K：不排序，只找最大的 K 个

module vlm_topk_selector #(
    parameter NUM_VALUES = 64,
    parameter TOP_K = 16,
    parameter INDEX_WIDTH = 6
)(
    input wire clk,
    input wire rst_n,
    input wire start,

    input wire [7:0] values [0:NUM_VALUES-1],
    output reg [INDEX_WIDTH-1:0] topk_indices [0:TOP_K-1],
    output reg done
);

    localparam IDLE = 2'd0;
    localparam SCAN = 2'd1;
    localparam DONE_STATE = 2'd2;

    reg [1:0] state;
    reg [7:0] scan_idx;

    // 当前找到的最小值
    reg [7:0] min_value;
    reg [INDEX_WIDTH-1:0] min_idx;

    // Top-K 数组
    reg [7:0] top_values [0:TOP_K-1];

    integer i;

    always @(posedge clk or negedge rst_n) begin
        if (!rst_n) begin
            state <= IDLE;
            scan_idx <= 0;
            done <= 0;
            for (i = 0; i < TOP_K; i = i + 1) begin
                top_values[i] <= 0;
                topk_indices[i] <= 0;
            end
        end else begin
            case (state)
                IDLE: begin
                    if (start) begin
                        state <= SCAN;
                        scan_idx <= 0;
                        done <= 0;
                        // 初始化为前 TOP_K 个
                        for (i = 0; i < TOP_K; i = i + 1) begin
                            top_values[i] <= values[i];
                            topk_indices[i] <= i;
                        end
                    end
                end

                SCAN: begin
                    if (scan_idx < NUM_VALUES) begin
                        // 找当前 Top-K 中的最小值
                        min_value = top_values[0];
                        min_idx = 0;
                        for (i = 1; i < TOP_K; i = i + 1) begin
                            if (top_values[i] < min_value) begin
                                min_value = top_values[i];
                                min_idx = i;
                            end
                        end

                        // 如果当前值更大，替换最小值
                        if (values[scan_idx] > min_value) begin
                            top_values[min_idx] <= values[scan_idx];
                            topk_indices[min_idx] <= scan_idx;
                        end

                        scan_idx <= scan_idx + 1;
                    end else begin
                        state <= DONE_STATE;
                    end
                end

                DONE_STATE: begin
                    done <= 1;
                    if (!start) begin
                        state <= IDLE;
                    end
                end
            endcase
        end
    end

endmodule

rtl/periph/vlm/vlm_scanner.v
`timescale 1ns / 1ps

// 混合版本：位置权重 + 图像梯度

module vlm_scanner #(
    parameter IMAGE_SIZE = 112,
    parameter PATCH_SIZE = 14,
    parameter GRID_SIZE = 8
)(
    input wire clk,
    input wire rst_n,
    input wire start,

    input wire [7:0] pixel_in,
    input wire pixel_valid,

    output reg [7:0] interest_out [0:GRID_SIZE*GRID_SIZE-1],
    output reg done
);

    localparam IDLE = 2'd0;
    localparam SCAN = 2'd1;
    localparam COMPUTE = 2'd2;
    localparam DONE_STATE = 2'd3;

    reg [1:0] state;
    reg [15:0] pixel_cnt;
    reg [7:0] image_buffer [0:IMAGE_SIZE*IMAGE_SIZE-1];

    integer i, row, col, img_i, img_j;
    integer dist_r, dist_c, dist_total;
    reg [15:0] position_weight;
    reg [15:0] gradient_score;
    reg [7:0] p00, p01, p10, p11;
    reg signed [8:0] gx, gy;

    always @(posedge clk or negedge rst_n) begin
        if (!rst_n) begin
            state <= IDLE;
            pixel_cnt <= 0;
            done <= 0;
            for (i = 0; i < GRID_SIZE*GRID_SIZE; i = i + 1)
                interest_out[i] <= 0;
        end else begin
            case (state)
                IDLE: begin
                    if (start) begin
                        state <= SCAN;
                        pixel_cnt <= 0;
                        done <= 0;
                    end
                end

                SCAN: begin
                    if (pixel_valid) begin
                        image_buffer[pixel_cnt] <= pixel_in;
                        pixel_cnt <= pixel_cnt + 1;

                        if (pixel_cnt == IMAGE_SIZE*IMAGE_SIZE - 1) begin
                            state <= COMPUTE;
                        end
                    end
                end

                COMPUTE: begin
                    // 计算每个 patch 的兴趣度
                    for (i = 0; i < GRID_SIZE*GRID_SIZE; i = i + 1) begin
                        row = i / GRID_SIZE;
                        col = i % GRID_SIZE;

                        // === 1. 位置权重 ===
                        dist_r = (row >= 4) ? (row - 4) : (4 - row);
                        dist_c = (col >= 4) ? (col - 4) : (4 - col);
                        dist_total = dist_r + dist_c;

                        if (dist_total == 0)
                            position_weight = 16'd1000;  // 中心超高权重
                        else if (dist_total == 1)
                            position_weight = 16'd800;
                        else if (dist_total == 2)
                            position_weight = 16'd500;
                        else if (dist_total == 3)
                            position_weight = 16'd200;
                        else
                            position_weight = 16'd0;

                        // === 2. 梯度特征 ===
                        img_i = row * PATCH_SIZE + (PATCH_SIZE >> 1);
                        img_j = col * PATCH_SIZE + (PATCH_SIZE >> 1);

                        if (img_i > 0 && img_i < IMAGE_SIZE-1 &&
                            img_j > 0 && img_j < IMAGE_SIZE-1) begin
                            p00 = image_buffer[(img_i-1)*IMAGE_SIZE + (img_j-1)];
                            p01 = image_buffer[(img_i-1)*IMAGE_SIZE + (img_j+1)];
                            p10 = image_buffer[(img_i+1)*IMAGE_SIZE + (img_j-1)];
                            p11 = image_buffer[(img_i+1)*IMAGE_SIZE + (img_j+1)];

                            gx = $signed({1'b0, p01}) - $signed({1'b0, p00});
                            gy = $signed({1'b0, p11}) - $signed({1'b0, p10});

                            gradient_score = (gx[8] ? -gx : gx) + (gy[8] ? -gy : gy);
                        end else begin
                            gradient_score = 0;
                        end

                        // === 3. 混合评分 ===
                        // 位置主导（80%），梯度辅助（20%）
                        interest_out[i] <= (position_weight + (gradient_score >> 2)) >> 3;
                    end
                    state <= DONE_STATE;
                end

                DONE_STATE: begin
                    done <= 1;
                    state <= IDLE;
                end
            endcase
        end
    end

endmodule

rtl/periph/vlm/vlm_preprocessing_top.v
`timescale 1ns / 1ps

module vlm_preprocessing_top #(
    parameter IMAGE_SIZE = 112,
    parameter GRID_SIZE = 8,
    parameter TOP_K = 16
)(
    input wire clk,
    input wire rst_n,
    input wire start,

    input wire [7:0] pixel_in,
    input wire pixel_valid,

    output wire [5:0] selected_indices [0:TOP_K-1],
    output wire done
);

    wire scanner_done;
    wire [7:0] interest_map [0:GRID_SIZE*GRID_SIZE-1];

    wire selector_start;
    wire selector_done;

    // 使用简单改进版扫描器
    vlm_scanner #(
        .IMAGE_SIZE(IMAGE_SIZE),
        .PATCH_SIZE(14),
        .GRID_SIZE(GRID_SIZE)
    ) u_scanner (
        .clk(clk),
        .rst_n(rst_n),
        .start(start),
        .pixel_in(pixel_in),
        .pixel_valid(pixel_valid),
        .interest_out(interest_map),
        .done(scanner_done)
    );

    vlm_topk_selector #(
        .NUM_VALUES(GRID_SIZE*GRID_SIZE),
        .TOP_K(TOP_K),
        .INDEX_WIDTH(6)
    ) u_selector (
        .clk(clk),
        .rst_n(rst_n),
        .start(selector_start),
        .values(interest_map),
        .topk_indices(selected_indices),
        .done(selector_done)
    );

    assign selector_start = scanner_done;
    assign done = selector_done;

endmodule

tb/vlm/vlm_preprocessing_tb.v
`timescale 1ns / 1ps

module vlm_preprocessing_tb;

    reg clk;
    reg rst_n;
    reg start;
    reg [7:0] pixel_in;
    reg pixel_valid;

    wire [5:0] selected_indices [0:15];
    wire done;

    // 使用改进版本
    vlm_preprocessing_top #(
        .IMAGE_SIZE(112),
        .GRID_SIZE(8),
        .TOP_K(16)
    ) dut (
        .clk(clk),
        .rst_n(rst_n),
        .start(start),
        .pixel_in(pixel_in),
        .pixel_valid(pixel_valid),
        .selected_indices(selected_indices),
        .done(done)
    );

    initial begin
        clk = 0;
        forever #5 clk = ~clk;
    end

    reg [7:0] test_image [0:12543];

    integer i;
    integer fd;
    initial begin
        $dumpfile("vlm_preprocessing.vcd");
        $dumpvars(0, vlm_preprocessing_tb);

        $readmemh("test_image.hex", test_image);

        rst_n = 0;
        start = 0;
        pixel_valid = 0;
        pixel_in = 0;

        #20;
        rst_n = 1;
        #10;

        start = 1;
        #10;
        start = 0;

        pixel_valid = 1;
        for (i = 0; i < 12544; i = i + 1) begin
            pixel_in = test_image[i];
            #10;
        end
        pixel_valid = 0;

        wait(done);
        #50;

        $display("=== Improved Top-16 Selected Indices ===");
        for (i = 0; i < 16; i = i + 1) begin
            $display("Index %2d: %d", i, selected_indices[i]);
        end

        fd = $fopen("output_indices.hex", "w");
        for (i = 0; i < 16; i = i + 1) begin
            $fwrite(fd, "%h\n", selected_indices[i]);
        end
        $fclose(fd);

        $display("Simulation complete!");
        $finish;
    end

    initial begin
        #5000000;
        $display("ERROR: Simulation timeout");
        $finish;
    end

endmodule

tb/vlm/vlm_preprocessing.vcd
$date
	Thu Jun 18 22:30:26 2026
$end
$version
	Icarus Verilog
$end
$timescale
	1ps
$end
$scope module vlm_preprocessing_tb $end
$var wire 1 ! done $end
$var reg 1 " clk $end
$var reg 8 # pixel_in [7:0] $end
$var reg 1 $ pixel_valid $end
$var reg 1 % rst_n $end
$var reg 1 & start $end
$var integer 32 ' fd [31:0] $end
$var integer 32 ( i [31:0] $end
$scope module dut $end
$var wire 1 " clk $end
$var wire 1 ! done $end
$var wire 8 ) pixel_in [7:0] $end
$var wire 1 $ pixel_valid $end
$var wire 1 % rst_n $end
$var wire 1 * selector_start $end
$var wire 1 & start $end
$var wire 1 + selector_done $end
$var wire 1 , scanner_done $end
$scope module u_scanner $end
$var wire 1 " clk $end
$var wire 8 - pixel_in [7:0] $end
$var wire 1 $ pixel_valid $end
$var wire 1 % rst_n $end
$var wire 1 & start $end
$var reg 1 , done $end
$var reg 16 . gradient_score [15:0] $end
$var reg 9 / gx [8:0] $end
$var reg 9 0 gy [8:0] $end
$var reg 8 1 p00 [7:0] $end
$var reg 8 2 p01 [7:0] $end
$var reg 8 3 p10 [7:0] $end
$var reg 8 4 p11 [7:0] $end
$var reg 16 5 pixel_cnt [15:0] $end
$var reg 16 6 position_weight [15:0] $end
$var reg 2 7 state [1:0] $end
$var integer 32 8 col [31:0] $end
$var integer 32 9 dist_c [31:0] $end
$var integer 32 : dist_r [31:0] $end
$var integer 32 ; dist_total [31:0] $end
$var integer 32 < i [31:0] $end
$var integer 32 = img_i [31:0] $end
$var integer 32 > img_j [31:0] $end
$var integer 32 ? row [31:0] $end
$upscope $end
$scope module u_selector $end
$var wire 1 " clk $end
$var wire 1 % rst_n $end
$var wire 1 * start $end
$var reg 1 + done $end
$var reg 6 @ min_idx [5:0] $end
$var reg 8 A min_value [7:0] $end
$var reg 8 B scan_idx [7:0] $end
$var reg 2 C state [1:0] $end
$var integer 32 D i [31:0] $end
$upscope $end
$upscope $end
$upscope $end
$enddefinitions $end
#0
$dumpvars
b10000 D
b0 C
b0 B
bx A
bx @
bx ?
bx >
bx =
b1000000 <
bx ;
bx :
bx 9
bx 8
b0 7
bx 6
b0 5
bx 4
bx 3
bx 2
bx 1
bx 0
bx /
bx .
b0 -
0,
0+
0*
b0 )
bx (
bx '
0&
0%
0$
b0 #
0"
0!
$end
#5000
b10000 D
b1000000 <
1"
#10000
0"
#15000
b1000000 <
b10000 D
1"
#20000
0"
1%
#25000
1"
#30000
0"
1&
#35000
b1 7
1"
#40000
0"
b110111 #
b110111 )
b110111 -
b0 (
1$
0&
#45000
b1 5
1"
#50000
0"
b1001110 #
b1001110 )
b1001110 -
b1 (
#55000
b10 5
1"
#60000
0"
b1110000 #
b1110000 )
b1110000 -
b10 (
#65000
b11 5
1"
#70000
0"
b1110010 #
b1110010 )
b1110010 -
b11 (
#75000
b100 5
1"
#80000
0"
b1010111 #
b1010111 )
b1010111 -
b100 (
#85000
b101 5
1"
#90000
0"
b110111 #
b110111 )
b110111 -
b101 (
#95000
b110 5
1"
#100000
0"
b1100010 #
b1100010 )
b1100010 -
b110 (
#105000
b111 5
1"
#110000
0"
b1110110 #
b1110110 )
b1110110 -
b111 (
#115000
b1000 5
1"
#120000
0"
b1110101 #
b1110101 )
b1110101 -
b1000 (
#125000
b1001 5
1"
#130000
0"
b1011000 #
b1011000 )
b1011000 -
b1001 (
#135000
b1010 5
1"
#140000
0"
b1000001 #
b1000001 )
b1000001 -
b1010 (
#145000
b1011 5
1"
#150000
0"
b110101 #
b110101 )
b110101 -
b1011 (
#155000
b1100 5
1"
#160000
0"
b101001 #
b101001 )
b101001 -
b1100 (
#165000
b1101 5
1"
#170000
0"
b1000100 #
b1000100 )
b1000100 -
b1101 (
#175000
b1110 5
1"
#180000
0"
b1010010 #
b1010010 )
b1010010 -
b1110 (
#185000
b1111 5
1"
#190000
0"
b1011101 #
b1011101 )
b1011101 -
b1111 (
#195000
b10000 5
1"
#200000
0"
b1011110 #
b1011110 )
b1011110 -
b10000 (
#205000
b10001 5
1"
#210000
0"
b1010100 #
b1010100 )
b1010100 -
b10001 (
#215000
b10010 5
1"
#220000
0"
b1011101 #
b1011101 )
b1011101 -
b10010 (
#225000
b10011 5
1"
#230000
0"
b1011111 #
b1011111 )
b1011111 -
b10011 (
#235000
b10100 5
1"
#240000
0"
b1101010 #
b1101010 )
b1101010 -
b10100 (
#245000
b10101 5
1"
#250000
0"
b1111010 #
b1111010 )
b1111010 -
b10101 (
#255000
b10110 5
1"
#260000
0"
b10110 (
#265000
b10111 5
1"
#270000
0"
b1111000 #
b1111000 )
b1111000 -
b10111 (
#275000
b11000 5
1"
#280000
0"
b1110111 #
b1110111 )
b1110111 -
b11000 (
#285000
b11001 5
1"
#290000
0"
b1111010 #
b1111010 )
b1111010 -
b11001 (
#295000
b11010 5
1"
#300000
0"
b1110011 #
b1110011 )
b1110011 -
b11010 (
#305000
b11011 5
1"
#310000
0"
b1101111 #
b1101111 )
b1101111 -
b11011 (
#315000
b11100 5
1"
#320000
0"
b11100 (
#325000
b11101 5
1"
#330000
0"
b1101000 #
b1101000 )
b1101000 -
b11101 (
#335000
b11110 5
1"
#340000
0"
b1101101 #
b1101101 )
b1101101 -
b11110 (
#345000
b11111 5
1"
#350000
0"
b1111000 #
b1111000 )
b1111000 -
b11111 (
#355000
b100000 5
1"
#360000
0"
b1111010 #
b1111010 )
b1111010 -
b100000 (
#365000
b100001 5
1"
#370000
0"
b10000000 #
b10000000 )
b10000000 -
b100001 (
#375000
b100010 5
1"
#380000
0"
b10000001 #
b10000001 )
b10000001 -
b100010 (
#385000
b100011 5
1"
#390000
0"
b10000000 #
b10000000 )
b10000000 -
b100011 (
#395000
b100100 5
1"
#400000
0"
b1111111 #
b1111111 )
b1111111 -
b100100 (
#405000
b100101 5
1"
#410000
0"
b1111100 #
b1111100 )
b1111100 -
b100101 (
#415000
b100110 5
1"
#420000
0"
b1111001 #
b1111001 )
b1111001 -
b100110 (
#425000
b100111 5
1"
#430000
0"
b1111100 #
b1111100 )
b1111100 -
b100111 (
#435000
b101000 5
1"
#440000
0"
b1110111 #
b1110111 )
b1110111 -
b101000 (
#445000
b101001 5
1"
#450000
0"
b1101110 #
b1101110 )
b1101110 -
b101001 (
#455000
b101010 5
1"
#460000
0"
b1101000 #
b1101000 )
b1101000 -
b101010 (
#465000
b101011 5
1"
#470000
0"
b1101101 #
b1101101 )
b1101101 -
b101011 (
#475000
b101100 5
1"
#480000
0"
b1111101 #
b1111101 )
b1111101 -
b101100 (
#485000
b101101 5
1"
#490000
0"
b10000001 #
b10000001 )
b10000001 -
b101101 (
#495000
b101110 5
1"
#500000
0"
b10000110 #
b10000110 )
b10000110 -
b101110 (
#505000
b101111 5
1"
#510000
0"
b1111011 #
b1111011 )
b1111011 -
b101111 (
#515000
b110000 5
1"
#520000
0"
b1101101 #
b1101101 )
b1101101 -
b110000 (
#525000
b110001 5
1"
#530000
0"
b1101011 #
b1101011 )
b1101011 -
b110001 (
#535000
b110010 5
1"
#540000
0"
b1011100 #
b1011100 )
b1011100 -
b110010 (
#545000
b110011 5
1"
#550000
0"
b1100100 #
b1100100 )
b1100100 -
b110011 (
#555000
b110100 5
1"
#560000
0"
b1111100 #
b1111100 )
b1111100 -
b110100 (
#565000
b110101 5
1"
#570000
0"
b10000101 #
b10000101 )
b10000101 -
b110101 (
#575000
b110110 5
1"
#580000
0"
b10001001 #
b10001001 )
b10001001 -
b110110 (
#585000
b110111 5
1"
#590000
0"
b10001111 #
b10001111 )
b10001111 -
b110111 (
#595000
b111000 5
1"
#600000
0"
b10011111 #
b10011111 )
b10011111 -
b111000 (
#605000
b111001 5
1"
#610000
0"
b10010110 #
b10010110 )
b10010110 -
b111001 (
#615000
b111010 5
1"
#620000
0"
b10001011 #
b10001011 )
b10001011 -
b111010 (
#625000
b111011 5
1"
#630000
0"
b10010011 #
b10010011 )
b10010011 -
b111011 (
#635000
b111100 5
1"
#640000
0"
b10001011 #
b10001011 )
b10001011 -
b111100 (
#645000
b111101 5
1"
#650000
0"
b1111100 #
b1111100 )
b1111100 -
b111101 (
#655000
b111110 5
1"
#660000
0"
b10000001 #
b10000001 )
b10000001 -
b111110 (
#665000
b111111 5
1"
#670000
0"
b10001110 #
b10001110 )
b10001110 -
b111111 (
#675000
b1000000 5
1"
#680000
0"
b10001100 #
b10001100 )
b10001100 -
b1000000 (
#685000
b1000001 5
1"
#690000
0"
b1110100 #
b1110100 )
b1110100 -
b1000001 (
#695000
b1000010 5
1"
#700000
0"
b1110011 #
b1110011 )
b1110011 -
b1000010 (
#705000
b1000011 5
1"
#710000
0"
b1110100 #
b1110100 )
b1110100 -
b1000011 (
#715000
b1000100 5
1"
#720000
0"
b1000100 (
#725000
b1000101 5
1"
#730000
0"
b1110010 #
b1110010 )
b1110010 -
b1000101 (
#735000
b1000110 5
1"
#740000
0"
b1000110 (
#745000
b1000111 5
1"
#750000
0"
b1111110 #
b1111110 )
b1111110 -
b1000111 (
#755000
b1001000 5
1"
#760000
0"
b1111101 #
b1111101 )
b1111101 -
b1001000 (
#765000
b1001001 5
1"
#770000
0"
b1111001 #
b1111001 )
b1111001 -
b1001001 (
#775000
b1001010 5
1"
#780000
0"
b10000010 #
b10000010 )
b10000010 -
b1001010 (
#785000
b1001011 5
1"
#790000
0"
b10001010 #
b10001010 )
b10001010 -
b1001011 (
#795000
b1001100 5
1"
#800000
0"
b1001100 (
#805000
b1001101 5
1"
#810000
0"
b1110101 #
b1110101 )
b1110101 -
b1001101 (
#815000
b1001110 5
1"
#820000
0"
b1011110 #
b1011110 )
b1011110 -
b1001110 (
#825000
b1001111 5
1"
#830000
0"
b1101101 #
b1101101 )
b1101101 -
b1001111 (
#835000
b1010000 5
1"
#840000
0"
b1100011 #
b1100011 )
b1100011 -
b1010000 (
#845000
b1010001 5
1"
#850000
0"
b1011010 #
b1011010 )
b1011010 -
b1010001 (
#855000
b1010010 5
1"
#860000
0"
b1010100 #
b1010100 )
b1010100 -
b1010010 (
#865000
b1010011 5
1"
#870000
0"
b1100101 #
b1100101 )
b1100101 -
b1010011 (
#875000
b1010100 5
1"
#880000
0"
b1111011 #
b1111011 )
b1111011 -
b1010100 (
#885000
b1010101 5
1"
#890000
0"
b1111100 #
b1111100 )
b1111100 -
b1010101 (
#895000
b1010110 5
1"
#900000
0"
b1101010 #
b1101010 )
b1101010 -
b1010110 (
#905000
b1010111 5
1"
#910000
0"
b1011110 #
b1011110 )
b1011110 -
b1010111 (
#915000
b1011000 5
1"
#920000
0"
b1110011 #
b1110011 )
b1110011 -
b1011000 (
#925000
b1011001 5
1"
#930000
0"
b1110000 #
b1110000 )
b1110000 -
b1011001 (
#935000
b1011010 5
1"
#940000
0"
b1000100 #
b1000100 )
b1000100 -
b1011010 (
#945000
b1011011 5
1"
#950000
0"
b1010110 #
b1010110 )
b1010110 -
b1011011 (
#955000
b1011100 5
1"
#960000
0"
b1111001 #
b1111001 )
b1111001 -
b1011100 (
#965000
b1011101 5
1"
#970000
0"
b1110111 #
b1110111 )
b1110111 -
b1011101 (
#975000
b1011110 5
1"
#980000
0"
b1111001 #
b1111001 )
b1111001 -
b1011110 (
#985000
b1011111 5
1"
#990000
0"
b10010010 #
b10010010 )
b10010010 -
b1011111 (
#995000
b1100000 5
1"
#1000000
0"
b10011101 #
b10011101 )
b10011101 -
b1100000 (
#1005000
b1100001 5
1"
#1010000
0"
b10011001 #
b10011001 )
b10011001 -
b1100001 (
#1015000
b1100010 5
1"
#1020000
0"
b10010111 #
b10010111 )
b10010111 -
b1100010 (
#1025000
b1100011 5
1"
#1030000
0"
b10011001 #
b10011001 )
b10011001 -
b1100011 (
#1035000
b1100100 5
1"
#1040000
0"
b10100100 #
b10100100 )
b10100100 -
b1100100 (
#1045000
b1100101 5
1"
#1050000
0"
b10100011 #
b10100011 )
b10100011 -
b1100101 (
#1055000
b1100110 5
1"
#1060000
0"
b10100100 #
b10100100 )
b10100100 -
b1100110 (
#1065000
b1100111 5
1"
#1070000
0"
b10011100 #
b10011100 )
b10011100 -
b1100111 (
#1075000
b1101000 5
1"
#1080000
0"
b10010010 #
b10010010 )
b10010010 -
b1101000 (
#1085000
b1101001 5
1"
#1090000
0"
b10000101 #
b10000101 )
b10000101 -
b1101001 (
#1095000
b1101010 5
1"
#1100000
0"
b10000001 #
b10000001 )
b10000001 -
b1101010 (
#1105000
b1101011 5
1"
#1110000
0"
b1110111 #
b1110111 )
b1110111 -
b1101011 (
#1115000
b1101100 5
1"
#1120000
0"
b1111110 #
b1111110 )
b1111110 -
b1101100 (
#1125000
b1101101 5
1"
#1130000
0"
b1111111 #
b1111111 )
b1111111 -
b1101101 (
#1135000
b1101110 5
1"
#1140000
0"
b1100110 #
b1100110 )
b1100110 -
b1101110 (
#1145000
b1101111 5
1"
#1150000
0"
b1100100 #
b1100100 )
b1100100 -
b1101111 (
#1155000
b1110000 5
1"
#1160000
0"
b1000010 #
b1000010 )
b1000010 -
b1110000 (
#1165000
b1110001 5
1"
#1170000
0"
b1100101 #
b1100101 )
b1100101 -
b1110001 (
#1175000
b1110010 5
1"
#1180000
0"
b10000001 #
b10000001 )
b10000001 -
b1110010 (
#1185000
b1110011 5
1"
#1190000
0"
b1110101 #
b1110101 )
b1110101 -
b1110011 (
#1195000
b1110100 5
1"
#1200000
0"
b1001011 #
b1001011 )
b1001011 -
b1110100 (
#1205000
b1110101 5
1"
#1210000
0"
b1000010 #
b1000010 )
b1000010 -
b1110101 (
#1215000
b1110110 5
1"
#1220000
0"
b10000001 #
b10000001 )
b10000001 -
b1110110 (
#1225000
b1110111 5
1"
#1230000
0"
b10001010 #
b10001010 )
b10001010 -
b1110111 (
#1235000
b1111000 5
1"
#1240000
0"
b1111000 #
b1111000 )
b1111000 -
b1111000 (
#1245000
b1111001 5
1"
#1250000
0"
b1010011 #
b1010011 )
b1010011 -
b1111001 (
#1255000
b1111010 5
1"
#1260000
0"
b111010 #
b111010 )
b111010 -
b1111010 (
#1265000
b1111011 5
1"
#1270000
0"
b110110 #
b110110 )
b110110 -
b1111011 (
#1275000
b1111100 5
1"
#1280000
0"
b1000001 #
b1000001 )
b1000001 -
b1111100 (
#1285000
b1111101 5
1"
#1290000
0"
b1011001 #
b1011001 )
b1011001 -
b1111101 (
#1295000
b1111110 5
1"
#1300000
0"
b1011011 #
b1011011 )
b1011011 -
b1111110 (
#1305000
b1111111 5
1"
#1310000
0"
b1011100 #
b1011100 )
b1011100 -
b1111111 (
#1315000
b10000000 5
1"
#1320000
0"
b10000000 (
#1325000
b10000001 5
1"
#1330000
0"
b1010010 #
b1010010 )
b1010010 -
b10000001 (
#1335000
b10000010 5
1"
#1340000
0"
b1011000 #
b1011000 )
b1011000 -
b10000010 (
#1345000
b10000011 5
1"
#1350000
0"
b1100110 #
b1100110 )
b1100110 -
b10000011 (
#1355000
b10000100 5
1"
#1360000
0"
b1101100 #
b1101100 )
b1101100 -
b10000100 (
#1365000
b10000101 5
1"
#1370000
0"
b1110101 #
b1110101 )
b1110101 -
b10000101 (
#1375000
b10000110 5
1"
#1380000
0"
b1111110 #
b1111110 )
b1111110 -
b10000110 (
#1385000
b10000111 5
1"
#1390000
0"
b1111011 #
b1111011 )
b1111011 -
b10000111 (
#1395000
b10001000 5
1"
#1400000
0"
b1110110 #
b1110110 )
b1110110 -
b10001000 (
#1405000
b10001001 5
1"
#1410000
0"
b1110101 #
b1110101 )
b1110101 -
b10001001 (
#1415000
b10001010 5
1"
#1420000
0"
b1110110 #
b1110110 )
b1110110 -
b10001010 (
#1425000
b10001011 5
1"
#1430000
0"
b1111001 #
b1111001 )
b1111001 -
b10001011 (
#1435000
b10001100 5
1"
#1440000
0"
b1101101 #
b1101101 )
b1101101 -
b10001100 (
#1445000
b10001101 5
1"
#1450000
0"
b1100011 #
b1100011 )
b1100011 -
b10001101 (
#1455000
b10001110 5
1"
#1460000
0"
b1110111 #
b1110111 )
b1110111 -
b10001110 (
#1465000
b10001111 5
1"
#1470000
0"
b10000000 #
b10000000 )
b10000000 -
b10001111 (
#1475000
b10010000 5
1"
#1480000
0"
b1111111 #
b1111111 )
b1111111 -
b10010000 (
#1485000
b10010001 5
1"
#1490000
0"
b10000101 #
b10000101 )
b10000101 -
b10010001 (
#1495000
b10010010 5
1"
#1500000
0"
b10000011 #
b10000011 )
b10000011 -
b10010010 (
#1505000
b10010011 5
1"
#1510000
0"
b1111100 #
b1111100 )
b1111100 -
b10010011 (
#1515000
b10010100 5
1"
#1520000
0"
b1110111 #
b1110111 )
b1110111 -
b10010100 (
#1525000
b10010101 5
1"
#1530000
0"
b1110100 #
b1110100 )
b1110100 -
b10010101 (
#1535000
b10010110 5
1"
#1540000
0"
b1110010 #
b1110010 )
b1110010 -
b10010110 (
#1545000
b10010111 5
1"
#1550000
0"
b1111000 #
b1111000 )
b1111000 -
b10010111 (
#1555000
b10011000 5
1"
#1560000
0"
b1110111 #
b1110111 )
b1110111 -
b10011000 (
#1565000
b10011001 5
1"
#1570000
0"
b1101111 #
b1101111 )
b1101111 -
b10011001 (
#1575000
b10011010 5
1"
#1580000
0"
b1101011 #
b1101011 )
b1101011 -
b10011010 (
#1585000
b10011011 5
1"
#1590000
0"
b1101010 #
b1101010 )
b1101010 -
b10011011 (
#1595000
b10011100 5
1"
#1600000
0"
b1110100 #
b1110100 )
b1110100 -
b10011100 (
#1605000
b10011101 5
1"
#1610000
0"
b1111011 #
b1111011 )
b1111011 -
b10011101 (
#1615000
b10011110 5
1"
#1620000
0"
b10011110 (
#1625000
b10011111 5
1"
#1630000
0"
b1110000 #
b1110000 )
b1110000 -
b10011111 (
#1635000
b10100000 5
1"
#1640000
0"
b1110001 #
b1110001 )
b1110001 -
b10100000 (
#1645000
b10100001 5
1"
#1650000
0"
b1101110 #
b1101110 )
b1101110 -
b10100001 (
#1655000
b10100010 5
1"
#1660000
0"
b1011010 #
b1011010 )
b1011010 -
b10100010 (
#1665000
b10100011 5
1"
#1670000
0"
b1011110 #
b1011110 )
b1011110 -
b10100011 (
#1675000
b10100100 5
1"
#1680000
0"
b1101000 #
b1101000 )
b1101000 -
b10100100 (
#1685000
b10100101 5
1"
#1690000
0"
b1101011 #
b1101011 )
b1101011 -
b10100101 (
#1695000
b10100110 5
1"
#1700000
0"
b10001011 #
b10001011 )
b10001011 -
b10100110 (
#1705000
b10100111 5
1"
#1710000
0"
b10110000 #
b10110000 )
b10110000 -
b10100111 (
#1715000
b10101000 5
1"
#1720000
0"
b11000010 #
b11000010 )
b11000010 -
b10101000 (
#1725000
b10101001 5
1"
#1730000
0"
b10100011 #
b10100011 )
b10100011 -
b10101001 (
#1735000
b10101010 5
1"
#1740000
0"
b10001110 #
b10001110 )
b10001110 -
b10101010 (
#1745000
b10101011 5
1"
#1750000
0"
b10101011 (
#1755000
b10101100 5
1"
#1760000
0"
b10001011 #
b10001011 )
b10001011 -
b10101100 (
#1765000
b10101101 5
1"
#1770000
0"
b10010111 #
b10010111 )
b10010111 -
b10101101 (
#1775000
b10101110 5
1"
#1780000
0"
b10011111 #
b10011111 )
b10011111 -
b10101110 (
#1785000
b10101111 5
1"
#1790000
0"
b10101111 (
#1795000
b10110000 5
1"
#1800000
0"
b10010101 #
b10010101 )
b10010101 -
b10110000 (
#1805000
b10110001 5
1"
#1810000
0"
b10000111 #
b10000111 )
b10000111 -
b10110001 (
#1815000
b10110010 5
1"
#1820000
0"
b10110010 (
#1825000
b10110011 5
1"
#1830000
0"
b1111001 #
b1111001 )
b1111001 -
b10110011 (
#1835000
b10110100 5
1"
#1840000
0"
b1110001 #
b1110001 )
b1110001 -
b10110100 (
#1845000
b10110101 5
1"
#1850000
0"
b1101110 #
b1101110 )
b1101110 -
b10110101 (
#1855000
b10110110 5
1"
#1860000
0"
b1110100 #
b1110100 )
b1110100 -
b10110110 (
#1865000
b10110111 5
1"
#1870000
0"
b1111100 #
b1111100 )
b1111100 -
b10110111 (
#1875000
b10111000 5
1"
#1880000
0"
b1110111 #
b1110111 )
b1110111 -
b10111000 (
#1885000
b10111001 5
1"
#1890000
0"
b1111101 #
b1111101 )
b1111101 -
b10111001 (
#1895000
b10111010 5
1"
#1900000
0"
b10000111 #
b10000111 )
b10000111 -
b10111010 (
#1905000
b10111011 5
1"
#1910000
0"
b10111011 (
#1915000
b10111100 5
1"
#1920000
0"
b10000110 #
b10000110 )
b10000110 -
b10111100 (
#1925000
b10111101 5
1"
#1930000
0"
b1101110 #
b1101110 )
b1101110 -
b10111101 (
#1935000
b10111110 5
1"
#1940000
0"
b1011010 #
b1011010 )
b1011010 -
b10111110 (
#1945000
b10111111 5
1"
#1950000
0"
b1100111 #
b1100111 )
b1100111 -
b10111111 (
#1955000
b11000000 5
1"
#1960000
0"
b1011000 #
b1011000 )
b1011000 -
b11000000 (
#1965000
b11000001 5
1"
#1970000
0"
b1011001 #
b1011001 )
b1011001 -
b11000001 (
#1975000
b11000010 5
1"
#1980000
0"
b1011000 #
b1011000 )
b1011000 -
b11000010 (
#1985000
b11000011 5
1"
#1990000
0"
b1100100 #
b1100100 )
b1100100 -
b11000011 (
#1995000
b11000100 5
1"
#2000000
0"
b10000110 #
b10000110 )
b10000110 -
b11000100 (
#2005000
b11000101 5
1"
#2010000
0"
b10000010 #
b10000010 )
b10000010 -
b11000101 (
#2015000
b11000110 5
1"
#2020000
0"
b10000101 #
b10000101 )
b10000101 -
b11000110 (
#2025000
b11000111 5
1"
